enrichlayer_client/__init__.py
enrichlayer_client/asyncio/__init__.py
enrichlayer_client/asyncio/base.py
enrichlayer_client/asyncio/library.py
enrichlayer_client/compat/__init__.py
enrichlayer_client/compat/monkey_patch.py
enrichlayer_client/config.py
enrichlayer_client/gevent/__init__.py
enrichlayer_client/gevent/base.py
enrichlayer_client/gevent/library.py
enrichlayer_client/models.py
enrichlayer_client/twisted/__init__.py
enrichlayer_client/twisted/base.py
enrichlayer_client/twisted/library.py
enrichlayer_api-0.1.0rc3.dist-info/METADATA
enrichlayer_api-0.1.0rc3.dist-info/WHEEL
enrichlayer_api-0.1.0rc3.dist-info/RECORD
